.gitignore
LICENSE
README.md
setup.cfg
setup.py
.idea/inspectionProfiles/Project_Default.xml
trippy/__init__.py
trippy/bgFinder.py
trippy/junk.py
trippy/pill.py
trippy/psf.py
trippy/psfStarChooser.py
trippy/trippy_utils.py
trippy/tzscale.py
trippy.egg-info/PKG-INFO
trippy.egg-info/SOURCES.txt
trippy.egg-info/dependency_links.txt
trippy.egg-info/pbr.json
trippy.egg-info/requires.txt
trippy.egg-info/top_level.txt
trippy/MCMCfit/MCMCfit.py
trippy/MCMCfit/__init__.py
trippy/scamp/__init__.py
trippy/scamp/makeParFiles.py
trippy/scamp/scamp.py
tutorial/def.param
tutorial/default.conv
tutorial/example.cat
tutorial/example.sex
tutorial/trippytutorial.ipynb