Metadata-Version: 2.1
Name: trippy
Version: 1.0
Summary: Pill aperture photometry for trailed astronomical sources
Home-page: https://github.com/fraserw/trippy
Author: Wesley Fraser
Author-email: westhefras@gmail.com
License: GNU
Download-URL: https://github.com/fraserw/trippy/tarball/0.1
Keywords: Photometry,Astronomy,PSF
Platform: UNKNOWN
Provides-Extra: MCMCfit
